[
    {
        "name": "McDonalds",
        "linkname": "mcdonalds",
        "user": "mcdo01",
        "pass": "$2b$10$EIbFZFz29zHMqmJNfDgOy.gNgUjyRaeqJyw16LhW3W0CSEQjPO7AW",
        "loggedIn": false,
        "image": "/common/Images/mcdo-umall.jpg",
        "imagesquare": "/common/Images/mcdo-umall-square.jpg",
        "description": "One of the most popular fast food chain that is well known for their burgers, fries, and chicken nuggets. The perfect choice for quick meals!",
        "landmark": "U_Mall",
        "rating": 5,
        "category": "fastfood",
        "price": 150,
        "maplink": "https://maps.app.goo.gl/nV6U4sp6NM7hys5n8",
        "revdata": 
        [
            {
                "revimg": "/common/Images/PFPs/Prince.jpg",
                "revname": "Buencamino, Prince",
                "revrating": "★★★★★",
                "rev": "Undebatebly the best fries and chicken nuggets in the world!",
                "hascomments": true,
                "likes" : [],
                "dislikes": ["mcdo01", "prince01", "blix02"],
                "comments": 
                [
                    {
                        "comimg": "/common/Images/PFPs/Micole.jpg",
                        "comname": "Chua, Micole",
                        "com": "Do not believe the words of this corporate lapdog!",
                        "likes" : [],
                "dislikes": ["mcdo01", "prince01", "blix02"],
                        "urlname":"/profile-page/Chua_Micole",
                        "notdeleted": true
                    }
                ],
                "urlname": "/profile-page/Buencamino_Prince",
                "notdeleted": true
            },
            {
                "revimg": "/common/Images/PFPs/catpfp.png",
                "revname": "Ruiz, Chester",
                "revrating": "★★★★★",
                "rev": "the mushroom pepper steak!",
                "hascomments": true,
                "likes" : ["mcdo01", "prince01", "blix02", "micole05"],
                "dislikes": ["mcdo01", "prince01", "blix02"],
                "comments": 
                [
                    {
                        "comimg": "/common/Images/mcdo-umall-square.jpg",
                        "comname": "McDonalds",
                        "com": "Nice to hear you enjoyed you like our mushroom pepper steak!",
                        "likes" : ["mcdo01", "prince01", "blix02", "micole05"],
                "dislikes": ["mcdo01", "prince01", "blix02"],
                        "urlname": "/restaurant/U_Mall/mcdonalds",
                        "notdeleted": true
                    }
                ],
                "urlname": "/profile-page/Ruiz_Chester",
                "notdeleted": true
            },
            {
                "revimg": "/common/Images/PFPs/Gaby.jpg",
                "revname": "Arco, Gaby",
                "revrating": "★★★★★",
                "rev": "The breakfast options were fire as always!",
                "hascomments": true,
                "likes" : ["mcdo01", "prince01", "blix02", "micole05"],
                "dislikes": ["mcdo01", "prince01", "blix02"],
                "comments": 
                [
                    {
                        "comimg": "/common/Images/mcdo-umall-square.jpg",
                        "comname": "McDonalds",
                        "com": "Nice to hear you enjoyed your experience!",
                        "likes" : ["mcdo01", "prince01", "blix02", "micole05"],
                        "dislikes": ["mcdo01", "prince01", "blix02"],
                        "urlname": "/restaurant/U_Mall/mcdonalds",
                        "notdeleted": true
                    }
                ],
                "urlname": "/profile-page/Arco_Gaby",
                "notdeleted": true
            }
        ],
        "reportdata": ["unhealthy food"]
    },

    {
        "name": "Starbucks",
        "linkname": "starbucks",
        "user": "starbs02",
        "pass": "$2b$10$EIbFZFz29zHMqmJNfDgOy.gNgUjyRaeqJyw16LhW3W0CSEQjPO7AW",
        "loggedIn": false,
        "image": "/common/Images/Starbs.png",
        "imagesquare": "/common/Images/Starbssquare.png",
        "description": "The globally popular coffee shop known for their drinks and pastries. A ideal place to be productive while sipping on some Starbucks coffee!",
        "landmark": "Burgundy",
        "rating": 3,
        "category": "coffee",
        "price": 250,
        "maplink": "https://maps.app.goo.gl/7dp926xAywX5Z1sS9",
        "revdata": 
        [
            {
                "revimg": "/common/Images/PFPs/Prince.jpg",
                "revname": "Buencamino, Prince",
                "revrating": "★★★★☆",
                "rev": "Overrated but still good. But please bring back the spinach tree",
                "hascomments": false,
                "likes" : ["mcdo01", "prince01", "blix02", "micole05"],
                "dislikes": ["mcdo01", "prince01", "blix02"],
                "urlname": "/profile-page/Buencamino_Prince",
                "notdeleted": true
            },
            {
                "revimg": "/common/Images/PFPs/catpfp.png",
                "revname": "Ruiz, Chester",
                "revrating": "★★★★☆",
                "rev": "expensive.. but it is popular for a reason.",
                "hascomments": false,
                
                "likes" : ["mcdo01", "prince01", "blix02", "micole05"],
                "dislikes": ["mcdo01", "prince01", "blix02"],
                "urlname": "/profile-page/Ruiz_Chester",
                "notdeleted": true
            },
            {
                "revimg": "/common/Images/PFPs/Blix.jpg",
                "revname": "Lingat, Blix",
                "revrating": "★★☆☆☆",
                "rev": "Very expensive, especially with inflation!",
                "hascomments": true,
                
                "likes" : ["mcdo01", "prince01", "blix02", "micole05"],
                "dislikes": ["mcdo01", "prince01", "blix02"],
                "comments": 
                [
                    {
                        "comimg": "/common/Images/PFPs/Micole.jpg",
                        "comname": "Chua, Micole",
                        "com": "I agree!",
                        
                "likes" : ["mcdo01", "prince01", "blix02", "micole05"],
                "dislikes": ["mcdo01", "prince01", "blix02"],
                        "urlname": "/profile-page/Chua_Micole",
                        "notdeleted": true
                    }
                ],
                "urlname": "/profile-page/Lingat_Blix",
                "notdeleted": true
            },
            {
                "revimg": "/common/Images/PFPs/Gaby.jpg",
                "revname": "Arco, Gaby",
                "revrating": "★★★★★",
                "rev": "The drinks were good and the sticker rewards even better!",
                "hascomments": false,
                
                "likes" : ["mcdo01", "prince01", "blix02", "micole05"],
                "dislikes": ["mcdo01", "prince01", "blix02"],
                "urlname": "/profile-page/Arco_Gaby",
                "notdeleted": true
            },
            {
                "revimg": "/common/Images/PFPs/Micole.jpg",
                "revname": "Chua, Micole",
                "revrating": "☆☆☆☆☆",
                "rev": "Somehow, even worse than coffee bean.",
                "hascomments": false,
                
                "likes" : ["mcdo01", "prince01", "blix02", "micole05"],
                "dislikes": ["mcdo01", "prince01", "blix02"],
                "urlname": "/profile-page/Chua_Micole",
                "notdeleted": true
            }
        ],
        "reportdata": ["coffee tastes like dirty water", "I never got my name spelt right"]
    },

    {
        "name": "KFC",
        "linkname": "kfc",
        "user": "kfc03",
        "pass": "$2b$10$EIbFZFz29zHMqmJNfDgOy.gNgUjyRaeqJyw16LhW3W0CSEQjPO7AW",
        "loggedIn": false,
        "image": "/common/Images/kfc.png",
        "imagesquare": "/common/Images/kfcsquare.png",
        "description": " The globally popular fast food chain that is well known for their fried chicken. Satisfy your cravings with some fried chicken paired with their iconic gravy!",
        "landmark": "U_Mall",
        "rating": 3,
        "category": "fastfood",
        "price": 125,
        "maplink": "https://maps.app.goo.gl/5Z3jzCtxKD8zpo788",
        "revdata": 
        [
            {
                "revimg": "/common/Images/PFPs/Blix.jpg",
                "revname": "Lingat, Blix",
                "revrating": "★★★★☆",
                "rev": "Usually good but the mushroom soup I ordered was cold",
                "hascomments": true,
                
                "likes" : ["mcdo01", "prince01", "blix02", "micole05"],
                "dislikes": ["mcdo01", "prince01", "blix02"],
                "comments": 
                [
                    {
                        "comimg": "/common/Images/kfcsquare.png",
                        "comname": "KFC",
                        "com": "Sorry to hear about your experience! We will do better.",
                        
                "likes" : ["mcdo01", "prince01", "blix02", "micole05"],
                "dislikes": ["mcdo01", "prince01", "blix02"],
                        "urlname": "/restaurant/U_Mall/kfc",
                        "notdeleted": true
                    }
                ],
                "urlname": "/profile-page/Lingat_Blix",
                "notdeleted": true
            },
            {
                "revimg": "/common/Images/PFPs/catpfp.png",
                "revname": "Ruiz, Chester",
                "revrating": "★★★☆☆",
                "rev": "It's alright.",
                "hascomments": false,
                
                "likes" : ["mcdo01", "prince01", "blix02", "micole05"],
                "dislikes": ["mcdo01", "prince01", "blix02"],
                "urlname": "/profile-page/Ruiz_Chester",
                "notdeleted": true
            },
            {
                "revimg": "/common/Images/PFPs/Micole.jpg",
                "revname": "Chua, Micole",
                "revrating": "★★☆☆☆",
                "rev": "The sisig bowl was too spicy, should've put more warnings",
                "hascomments": true,
                
                "likes" : ["mcdo01", "prince01", "blix02", "micole05"],
                "dislikes": ["mcdo01", "prince01", "blix02"],
                "comments": 
                [
                    {
                        "comimg": "/common/Images/kfcsquare.png",
                        "comname": "KFC",
                        "com": "Sorry to hear about your experience! We will list down the spicy levels next time!",
                        
                "likes" : ["mcdo01", "prince01", "blix02", "micole05"],
                "dislikes": ["mcdo01", "prince01", "blix02"],
                        "urlname": "/restaurant/U_Mall/kfc",
                        "notdeleted": true
                    }
                ],
                "urlname": "/profile-page/Chua_Micole",
                "notdeleted": true
            }
        ],
        "reportdata": ["I got diarrhea"]
    },

    {
        "name": "Army Navy",
        "linkname": "army_navy",
        "user": "armynavy04",
        "pass": "$2b$10$EIbFZFz29zHMqmJNfDgOy.gNgUjyRaeqJyw16LhW3W0CSEQjPO7AW",
        "loggedIn": false,
        "image": "/common/Images/armynavy.png",
        "imagesquare": "/common/Images/armynavysquare.png",
        "description": "A well-known restaurant that is renowned for their tacos, burritos, and burgers. Chow down on a variety of comforting meals in Army Navy!",
        "landmark": "Burgundy",
        "rating": 5,
        "category": "fastfood",
        "price": 215,
        "maplink": "https://maps.app.goo.gl/26PtNmxaXeLsbzrb6",
        "revdata": 
        [
            {
                "revimg": "/common/Images/PFPs/Blix.jpg",
                "revname": "Lingat, Blix",
                "revrating": "★★★★★",
                "rev": "The tacos were magnificent, would come again!",
                "hascomments": true,
                
                "likes" : ["mcdo01", "prince01", "blix02", "micole05"],
                "dislikes": ["mcdo01", "prince01", "blix02"],
                "comments": 
                [
                    {
                        "comimg": "/common/Images/PFPs/Gaby.jpg",
                        "comname": "Arco, Gaby",
                        "com": "I agree!!",
                        
                "likes" : ["mcdo01", "prince01", "blix02", "micole05"],
                "dislikes": ["mcdo01", "prince01", "blix02"],
                        "urlname": "/profile-page/Arco_Gaby",
                        "notdeleted": true
                    }
                ],
                "urlname": "/profile-page/Lingat_Blix",
                "notdeleted": true
            },
            {
                "revimg": "/common/Images/PFPs/Gaby.jpg",
                "revname": "Arco, Gaby",
                "revrating": "★★★★★",
                "rev": "The carbonara was flavorful and worth the price!",
                "hascomments": false,
                
                "likes" : ["mcdo01", "prince01", "blix02", "micole05"],
                "dislikes": ["mcdo01", "prince01", "blix02"],
                "urlname": "/profile-page/Arco_Gaby",
                "notdeleted": true
            }
        ],
        "reportdata": []
    },

    {
        "name": "The Coffee Bean & Tea Leaf",
        "linkname": "coffee_bean",
        "user": "coffbean05",
        "pass": "$2b$10$EIbFZFz29zHMqmJNfDgOy.gNgUjyRaeqJyw16LhW3W0CSEQjPO7AW",
        "loggedIn": false,
        "image": "/common/Images/coffeebean.jpg",
        "imagesquare": "/common/Images/coffeebean.jpg",
        "description": " A coffee shop that serves some of the best ice-blended coffee and drinks as well as a variety of pastries and meals. Relax and enjoy the view at the Coffee Bean and Tea Leaf!",
        "landmark": "DLSU",
        "rating": 3.5,
        "category": "coffee",
        "price": 250,
        "maplink": "https://maps.app.goo.gl/wbhHNQggXdu29TQE7",
        "revdata": 
        [
            {
                "revimg": "/common/Images/PFPs/Micole.jpg",
                "revname": "Chua, Micole",
                "revrating": "★★☆☆☆",
                "rev": "A steep price tag for mid drinks.",
                "hascomments": false,
                
                "likes" : ["mcdo01", "prince01", "blix02", "micole05"],
                "dislikes": ["mcdo01", "prince01", "blix02"],
                "urlname": "/profile-page/Chua_Micole",
                "notdeleted": true
            },
            {
                "revimg": "/common/Images/PFPs/Prince.jpg",
                "revname": "Buencamino, Prince",
                "revrating": "★★★★★",
                "rev": "Much better than Starbucks!",
                "hascomments": true,
                
                "likes" : ["mcdo01", "prince01", "blix02", "micole05"],
                "dislikes": ["mcdo01", "prince01", "blix02"],
                "comments": 
                [
                    {
                        "comimg": "/common/Images/PFPs/Micole.jpg",
                        "comname": "Chua, Micole",
                        "com": "Ha? Hatdog!",
                        
                "likes" : ["mcdo01", "prince01", "blix02", "micole05"],
                "dislikes": ["mcdo01", "prince01", "blix02"],
                        "urlname": "/profile-page/Chua_Micole",
                        "notdeleted": true
                    }
                ],
                "urlname": "/profile-page/Buencamino_Prince",
                "notdeleted": true
            }
        ],
        "reportdata": ["There are never empty seats"]
    }
]


